.gitignore
LICENSE.md
MANIFEST.in
README.md
pyproject.toml
setup.py
stdpipe/__init__.py
stdpipe/astrometry.py
stdpipe/catalogs.py
stdpipe/cutouts.py
stdpipe/db.py
stdpipe/lcs.py
stdpipe/photometry.py
stdpipe/photometry_iraf.py
stdpipe/photometry_measure.py
stdpipe/photometry_model.py
stdpipe/photometry_psf.py
stdpipe/pipeline.py
stdpipe/plots.py
stdpipe/psf.py
stdpipe/resolve.py
stdpipe/subtraction.py
stdpipe/templates.py
stdpipe/utils.py
stdpipe.egg-info/PKG-INFO
stdpipe.egg-info/SOURCES.txt
stdpipe.egg-info/dependency_links.txt
stdpipe.egg-info/not-zip-safe
stdpipe.egg-info/requires.txt
stdpipe.egg-info/top_level.txt
stdpipe/data/legacysurvey.py
stdpipe/data/legacysurvey_bricks.fits.gz
stdpipe/data/ps1skycells.txt
stdpipe/data/ps1skycells.txt.orig
tests/test_astrometry.py
tests/test_catalogs.py
tests/test_photometry.py
tests/test_photometry_iraf.py
tests/test_photometry_measure.py
tests/test_photometry_model.py
tests/test_photometry_psf.py
tests/test_pipeline.py
tests/test_utils.py