Metadata-Version: 2.4
Name: stdpipe
Version: 0.3.0
Summary: Simple Transient Detection Pipeline
Author-email: Sergey Karpov <karpov.sv@gmail.com>
Maintainer-email: Sergey Karpov <karpov.sv@gmail.com>
License: MIT License
Project-URL: Homepage, https://github.com/karpov-sv/stdpipe
Project-URL: Documentation, https://stdpipe.readthedocs.io/
Project-URL: Repository, https://github.com/karpov-sv/stdpipe
Project-URL: Bug Tracker, https://github.com/karpov-sv/stdpipe/issues
Project-URL: Changelog, https://github.com/karpov-sv/stdpipe/commits/master
Keywords: astronomy,astrophysics,transients,photometry,astrometry,image-processing,pipeline
Classifier: Development Status :: 4 - Beta
Classifier: Intended Audience :: Science/Research
Classifier: License :: OSI Approved :: MIT License
Classifier: Operating System :: OS Independent
Classifier: Programming Language :: Python :: 3
Classifier: Programming Language :: Python :: 3.8
Classifier: Programming Language :: Python :: 3.9
Classifier: Programming Language :: Python :: 3.10
Classifier: Programming Language :: Python :: 3.11
Classifier: Programming Language :: Python :: 3.12
Classifier: Programming Language :: Python :: 3.13
Classifier: Topic :: Scientific/Engineering :: Astronomy
Classifier: Topic :: Scientific/Engineering :: Image Processing
Requires-Python: >=3.8
License-File: LICENSE.md
Requires-Dist: numpy
Requires-Dist: scipy
Requires-Dist: astropy>=4.1
Requires-Dist: matplotlib
Requires-Dist: astroquery>0.4.1
Requires-Dist: sep
Requires-Dist: astroscrappy
Requires-Dist: photutils>=2.2
Requires-Dist: scikit-image
Requires-Dist: statsmodels
Requires-Dist: tqdm
Requires-Dist: regions
Requires-Dist: python-dateutil
Requires-Dist: requests
Requires-Dist: sip_tpv
Requires-Dist: pyfftw
Provides-Extra: dev
Requires-Dist: pytest>=6.0; extra == "dev"
Requires-Dist: pytest-cov>=2.10; extra == "dev"
Requires-Dist: pytest-xdist>=2.0; extra == "dev"
Requires-Dist: pytest-mock>=3.0; extra == "dev"
Requires-Dist: pytest-timeout>=2.0; extra == "dev"
Requires-Dist: pytest-benchmark>=3.4; extra == "dev"
Requires-Dist: hypothesis>=6.0; extra == "dev"
Provides-Extra: docs
Requires-Dist: sphinx>=4.0; extra == "docs"
Requires-Dist: sphinx-rtd-theme; extra == "docs"
Requires-Dist: sphinx-math-dollar; extra == "docs"
Requires-Dist: numpydoc; extra == "docs"
Requires-Dist: myst-parser; extra == "docs"
Requires-Dist: sphinxcontrib-apidoc; extra == "docs"
Requires-Dist: sphinx-prompt; extra == "docs"
Provides-Extra: adaptive
Requires-Dist: powerbin; extra == "adaptive"
Provides-Extra: all
Requires-Dist: stdpipe[adaptive,dev,docs]; extra == "all"
Dynamic: license-file
